docs/_downloads/29a3c68eabc4dfce3cc2b8f28cbf7499/test.py
docs/_downloads/9a3170560eff0e8080a7006943761820/PubSubTs.template.py
docs/_downloads/a8af61e20b3888c79a5cc6ff79c43632/HelloWorldPy.template.py
docs/_downloads/cb75f7c5c4638fa0c1e352dc3e3ce4c7/HelloWorldTs.template.py
docs/build/_downloads/29a3c68eabc4dfce3cc2b8f28cbf7499/test.py
docs/build/_downloads/9a3170560eff0e8080a7006943761820/PubSubTs.template.py
docs/build/_downloads/a8af61e20b3888c79a5cc6ff79c43632/HelloWorldPy.template.py
docs/build/_downloads/cb75f7c5c4638fa0c1e352dc3e3ce4c7/HelloWorldTs.template.py
docs/build/html/_downloads/29a3c68eabc4dfce3cc2b8f28cbf7499/test.py
docs/build/html/_downloads/9a3170560eff0e8080a7006943761820/PubSubTs.template.py
docs/build/html/_downloads/a8af61e20b3888c79a5cc6ff79c43632/HelloWorldPy.template.py
docs/build/html/_downloads/cb75f7c5c4638fa0c1e352dc3e3ce4c7/HelloWorldTs.template.py
docs/source/conf.py
sylk/__init__.py
sylk/__version__.py
sylk/config.py
sylk/architect/__init__.py
sylk/architect/commands.py
sylk/architect/hooks.py
sylk/architect/invoker.py
sylk/architect/interfaces/__init__.py
sylk/architect/recievers/__init__.py
sylk/builder/__init__.py
sylk/builder/plugins/SylkBase.py
sylk/builder/plugins/SylkGoClient.py
sylk/builder/plugins/SylkGoServer.py
sylk/builder/plugins/SylkJsClient.py
sylk/builder/plugins/SylkJsServer.py
sylk/builder/plugins/SylkMigrate.py
sylk/builder/plugins/SylkPlugins.py
sylk/builder/plugins/SylkProto.py
sylk/builder/plugins/SylkPyClient.py
sylk/builder/plugins/SylkPyServer.py
sylk/builder/plugins/SylkReadme.py
sylk/builder/plugins/SylkTsClient.py
sylk/builder/plugins/SylkTsServer.py
sylk/builder/plugins/SylkWebpackClient.py
sylk/builder/plugins/__init__.py
sylk/builder/plugins/static.py
sylk/builder/src/__init__.py
sylk/builder/src/hookspecs.py
sylk/builder/src/lru.py
sylk/builder/src/main.py
sylk/cli/__init__.py
sylk/cli/__main__.py
sylk/cli/main.py
sylk/cli/prompter.py
sylk/cli/theme.py
sylk/cli/commands/__init__.py
sylk-0.4.2.dist-info/LICENSE
sylk-0.4.2.dist-info/METADATA
sylk-0.4.2.dist-info/WHEEL
sylk-0.4.2.dist-info/entry_points.txt
sylk-0.4.2.dist-info/top_level.txt
sylk-0.4.2.dist-info/RECORD
